LICENSE
MANIFEST.in
README.rst
VERSION
setup.cfg
setup.py
maketools/__init__.py
maketools.egg-info/PKG-INFO
maketools.egg-info/SOURCES.txt
maketools.egg-info/dependency_links.txt
maketools.egg-info/not-zip-safe
maketools.egg-info/top_level.txt