Metadata-Version: 1.0
Name: maketools
Version: 0.1.4
Summary: Add build prerequisites to your python project.
Home-page: https://github.com/nickw444/python-maketools
Author: Nick Whyte
Author-email: nick@nickwhyte.com
License: UNKNOWN
Platform: UNKNOWN
